altslice.py
altslice-0.1.0.dist-info/DESCRIPTION.rst
altslice-0.1.0.dist-info/METADATA
altslice-0.1.0.dist-info/RECORD
altslice-0.1.0.dist-info/WHEEL
altslice-0.1.0.dist-info/metadata.json
altslice-0.1.0.dist-info/top_level.txt
